email_to_soup/__init__.py
email_to_soup/main.py
tests/__init__.py
tests/test_email_to_soup.py
tests/fixtures/__init__.py
tests/fixtures/test_email.eml
email_to_soup-0.0.10.dist-info/LICENSE
email_to_soup-0.0.10.dist-info/METADATA
email_to_soup-0.0.10.dist-info/WHEEL
email_to_soup-0.0.10.dist-info/top_level.txt
email_to_soup-0.0.10.dist-info/RECORD
